halborn_ctf/__init__.py
halborn_ctf/cli.py
halborn_ctf/functions.py
halborn_ctf/generator.py
halborn_ctf/shell.py
halborn_ctf/state.py
halborn_ctf/templates.py
halborn_ctf/generator/Dockerfile.base
halborn_ctf/generator/challenge.base.py
halborn_ctf/network/__init__.py
halborn_ctf/network/_generic.py
halborn_ctf/network/filters/__init__.py
halborn_ctf/network/filters/_utils.py
halborn_ctf/network/filters/json_rpc.py
halborn_ctf/network/filters/_json_rpc/filter_json_rpc_method.py
halborn_ctf/network/filters/_json_rpc/whitelist_json_rpc_method.py
halborn_ctf-0.1.20.dist-info/LICENSE.txt
halborn_ctf-0.1.20.dist-info/METADATA
halborn_ctf-0.1.20.dist-info/WHEEL
halborn_ctf-0.1.20.dist-info/entry_points.txt
halborn_ctf-0.1.20.dist-info/top_level.txt
halborn_ctf-0.1.20.dist-info/RECORD
