Metadata-Version: 2.1
Name: halborn-ctf
Version: 0.1.20
Summary: Add a short description here!
Home-page: https://github.com/HalbornAcademy/halborn_ctf
Author: ferran.celades
Author-email: ferran.celades@halborn.com
License: MIT
Project-URL: Documentation, https://halborn-ctf.readthedocs.io/
Platform: any
Classifier: Development Status :: 4 - Beta
Classifier: Programming Language :: Python
License-File: LICENSE.txt
Requires-Dist: mitmproxy (>=9.0.1)
Requires-Dist: flask (<2.4,>=1.1.1)
Requires-Dist: flask-cors (>=3.0.10)
Requires-Dist: requests (<3,>=2.29.0)
Requires-Dist: python-on-whales (>=0.61.0)
Requires-Dist: jinja2 (>=3.1.2)
Requires-Dist: importlib-metadata ; python_version < "3.8"
Provides-Extra: testing
Requires-Dist: setuptools ; extra == 'testing'
Requires-Dist: pytest ; extra == 'testing'
Requires-Dist: pytest-cov ; extra == 'testing'
